bigbucks_port/__init__.py
bigbucks_port/portfolio.py
bigbucks_port-0.1.1.dist-info/LICENSE
bigbucks_port-0.1.1.dist-info/METADATA
bigbucks_port-0.1.1.dist-info/WHEEL
bigbucks_port-0.1.1.dist-info/top_level.txt
bigbucks_port-0.1.1.dist-info/RECORD
