Metadata-Version: 2.1
Name: bigbucks-port
Version: 0.1.1
Summary: A package used for portfolio analysis in Fintech512
Author: Wenjie Cui
License-File: LICENSE
